anillo_sentry
