Metadata-Version: 1.1
Name: anillo-sentry
Version: 0.1.1
Summary: Sentry integration middleware for anillo
Home-page: https://github.com/jespino/anillo_sentry
Author: Jesús Espino García
Author-email: jespinog@gmail.com
License: BSD
Keywords: sentry,anillo
Platform: UNKNOWN
Classifier: Programming Language :: Python
Classifier: Programming Language :: Python :: 3
Classifier: Programming Language :: Python :: 3.3
Classifier: Programming Language :: Python :: 3.4
Classifier: Programming Language :: Python :: 3.5
Classifier: Development Status :: 3 - Alpha
Classifier: Intended Audience :: Developers
Classifier: License :: OSI Approved :: BSD License
Classifier: Operating System :: OS Independent
Classifier: Programming Language :: Python
Classifier: Topic :: Internet :: WWW/HTTP
